autotag/old.py
autotag/utils.py
autotag/__init__.py
autotag/autotag.py
autotag/stopwords.py
autotag-0.457.dist-info/METADATA
autotag-0.457.dist-info/metadata.json
autotag-0.457.dist-info/DESCRIPTION.rst
autotag-0.457.dist-info/top_level.txt
autotag-0.457.dist-info/RECORD
autotag-0.457.dist-info/WHEEL
