Metadata-Version: 2.0
Name: autotag
Version: 0.457
Summary: Tag suggestion according to text 
Home-page: https://github.com/jvalansi/autotag
Author: Jordan Valansi
Author-email: jvalansi_autotag@gmail.com
License: MIT
Platform: UNKNOWN
Requires-Dist: nltk (==3.0.0)
